{
  "generated_at": "2026-06-02T18:20:43.196739Z",
  "enabled": true,
  "interval_seconds": 60,
  "ready": true,
  "readiness_errors": [],
  "last_run_at": "2026-06-02T18:20:23.653840Z",
  "last_success_at": null,
  "last_error": "runtime_engine: status push failed (RuntimeError: Statuspage API PATCH /pages/v0hwlmly3pd2/components/replace-with-statuspage-component-id-runtime-engine failed with 404: {\"error\":\"Couldn't find Component with [WHERE \\\"components\\\".\\\"page_id\\\" = $1 AND \\\"components\\\".\\\"code\\\" = $2]\"}); auth_api: status push failed (RuntimeError: Statuspage API PATCH /pages/v0hwlmly3pd2/components/replace-with-statuspage-component-id-auth-api failed with 404: {\"error\":\"Couldn't find Component with [WHERE \\\"components\\\".\\\"page_id\\\" = $1 AND \\\"components\\\".\\\"code\\\" = $2]\"}); creator_dashboard: status push failed (RuntimeError: Statuspage API PATCH /pages/v0hwlmly3pd2/components/replace-with-statuspage-component-id-creator-dashboard failed with 404: {\"error\":\"Couldn't find Component with [WHERE \\\"components\\\".\\\"page_id\\\" = $1 AND \\\"components\\\".\\\"code\\\" = $2]\"}); admin_dashboard: status push failed (RuntimeError: Statuspage API PATCH /pages/v0hwlmly3pd2/components/replace-with-statuspage-component-id-admin-dashboard failed with 404: {\"error\":\"Couldn't find Component with [WHERE \\\"components\\\".\\\"page_id\\\" = $1 AND \\\"components\\\".\\\"code\\\" = $2]\"}); public_pages: status push failed (RuntimeError: Statuspage API PATCH /pages/v0hwlmly3pd2/components/replace-with-statuspage-component-id-public-pages failed with 404: {\"error\":\"Couldn't find Component with [WHERE \\\"components\\\".\\\"page_id\\\" = $1 AND \\\"components\\\".\\\"code\\\" = $2]\"}); support_hub: status push failed (RuntimeError: Statuspage API PATCH /pages/v0hwlmly3pd2/components/replace-with-statuspage-component-id-support-hub failed with 404: {\"error\":\"Couldn't find Component with [WHERE \\\"components\\\".\\\"page_id\\\" = $1 AND \\\"components\\\".\\\"code\\\" = $2]\"}); account_session: status push failed (RuntimeError: Statuspage API PATCH /pages/v0hwlmly3pd2/components/replace-with-statuspage-component-id-account-session failed with 404: {\"error\":\"Couldn't find Component with [WHERE \\\"components\\\".\\\"page_id\\\" = $1 AND \\\"components\\\".\\\"code\\\" = $2]\"}); automation_trigger: status push failed (RuntimeError: Statuspage API PATCH /pages/v0hwlmly3pd2/components/replace-with-statuspage-component-id-automation-trigger failed with 404: {\"error\":\"Couldn't find Component with [WHERE \\\"components\\\".\\\"page_id\\\" = $1 AND \\\"components\\\".\\\"code\\\" = $2]\"}); telemetry_usage: status push failed (RuntimeError: Statuspage API PATCH /pages/v0hwlmly3pd2/components/replace-with-statuspage-component-id-telemetry-usage failed with 404: {\"error\":\"Couldn't find Component with [WHERE \\\"components\\\".\\\"page_id\\\" = $1 AND \\\"components\\\".\\\"code\\\" = $2]\"})",
  "components": {
    "account_session": {
      "component_id": "replace-with-statuspage-component-id-account-session",
      "computed_status": "operational",
      "last_pushed_status": null,
      "last_pushed_at": null,
      "consecutive_failures": 0,
      "consecutive_successes": 34,
      "last_check": {
        "ok": true,
        "status_code": 200,
        "latency_ms": 31,
        "error": null,
        "checked_at": "2026-06-02T18:20:29.858916Z"
      }
    },
    "admin_dashboard": {
      "component_id": "replace-with-statuspage-component-id-admin-dashboard",
      "computed_status": "operational",
      "last_pushed_status": null,
      "last_pushed_at": null,
      "consecutive_failures": 0,
      "consecutive_successes": 34,
      "last_check": {
        "ok": true,
        "status_code": 200,
        "latency_ms": 1296,
        "error": null,
        "checked_at": "2026-06-02T18:20:28.260472Z"
      }
    },
    "auth_api": {
      "component_id": "replace-with-statuspage-component-id-auth-api",
      "computed_status": "operational",
      "last_pushed_status": null,
      "last_pushed_at": null,
      "consecutive_failures": 0,
      "consecutive_successes": 34,
      "last_check": {
        "ok": true,
        "status_code": 200,
        "latency_ms": 30,
        "error": null,
        "checked_at": "2026-06-02T18:20:25.699898Z"
      }
    },
    "automation_trigger": {
      "component_id": "replace-with-statuspage-component-id-automation-trigger",
      "computed_status": "major_outage",
      "last_pushed_status": null,
      "last_pushed_at": null,
      "consecutive_failures": 34,
      "consecutive_successes": 0,
      "last_check": {
        "ok": false,
        "status_code": null,
        "latency_ms": 2015,
        "error": "ConnectionError: HTTPConnectionPool(host='127.0.0.1', port=8787): Max retries exceeded with url: /api/health?scope=automation_trigger (Caused by NewConnectionError('<urllib3.connection.HTTPConnection object at 0x0000015455EA2250>: Failed to establish a new connection: [WinError 10061] No connection could be made because the target machine actively refused it'))",
        "checked_at": "2026-06-02T18:20:31.871561Z"
      }
    },
    "creator_dashboard": {
      "component_id": "replace-with-statuspage-component-id-creator-dashboard",
      "computed_status": "operational",
      "last_pushed_status": null,
      "last_pushed_at": null,
      "consecutive_failures": 0,
      "consecutive_successes": 34,
      "last_check": {
        "ok": true,
        "status_code": 200,
        "latency_ms": 1266,
        "error": null,
        "checked_at": "2026-06-02T18:20:26.967594Z"
      }
    },
    "public_pages": {
      "component_id": "replace-with-statuspage-component-id-public-pages",
      "computed_status": "operational",
      "last_pushed_status": null,
      "last_pushed_at": null,
      "consecutive_failures": 0,
      "consecutive_successes": 34,
      "last_check": {
        "ok": true,
        "status_code": 200,
        "latency_ms": 1282,
        "error": null,
        "checked_at": "2026-06-02T18:20:29.549049Z"
      }
    },
    "runtime_engine": {
      "component_id": "replace-with-statuspage-component-id-runtime-engine",
      "computed_status": "major_outage",
      "last_pushed_status": null,
      "last_pushed_at": null,
      "consecutive_failures": 34,
      "consecutive_successes": 0,
      "last_check": {
        "ok": false,
        "status_code": null,
        "latency_ms": 2016,
        "error": "ConnectionError: HTTPConnectionPool(host='127.0.0.1', port=8787): Max retries exceeded with url: /api/health?scope=runtime_engine (Caused by NewConnectionError('<urllib3.connection.HTTPConnection object at 0x0000015455B0CE90>: Failed to establish a new connection: [WinError 10061] No connection could be made because the target machine actively refused it'))",
        "checked_at": "2026-06-02T18:20:25.668327Z"
      }
    },
    "support_hub": {
      "component_id": "replace-with-statuspage-component-id-support-hub",
      "computed_status": "operational",
      "last_pushed_status": null,
      "last_pushed_at": null,
      "consecutive_failures": 0,
      "consecutive_successes": 34,
      "last_check": {
        "ok": true,
        "status_code": 200,
        "latency_ms": 280,
        "error": null,
        "checked_at": "2026-06-02T18:20:29.823676Z"
      }
    },
    "telemetry_usage": {
      "component_id": "replace-with-statuspage-component-id-telemetry-usage",
      "computed_status": "major_outage",
      "last_pushed_status": null,
      "last_pushed_at": null,
      "consecutive_failures": 34,
      "consecutive_successes": 0,
      "last_check": {
        "ok": false,
        "status_code": null,
        "latency_ms": 2031,
        "error": "ConnectionError: HTTPConnectionPool(host='127.0.0.1', port=8787): Max retries exceeded with url: /api/health?scope=telemetry_usage (Caused by NewConnectionError('<urllib3.connection.HTTPConnection object at 0x0000015455BB6650>: Failed to establish a new connection: [WinError 10061] No connection could be made because the target machine actively refused it'))",
        "checked_at": "2026-06-02T18:20:33.900000Z"
      }
    }
  },
  "last_run_source": "loop"
}